main.py
show_image.py
image_viewer/__init__.py
image_viewer/cache.py
image_viewer/kitty.py
image_viewer/pdf_processor.py
image_viewer/processor.py
image_viewer/show.py
image_viewer/terminal.py
image_viewer/viewer.py
pmv-0.2.1.dist-info/licenses/LICENSE
pmv-0.2.1.dist-info/METADATA
pmv-0.2.1.dist-info/WHEEL
pmv-0.2.1.dist-info/entry_points.txt
pmv-0.2.1.dist-info/top_level.txt
pmv-0.2.1.dist-info/RECORD
