Metadata-Version: 2.4
Name: pmv
Version: 0.2.1
Summary: A TUI image viewer for Kitty terminal with keyboard navigation and PDF support
Author-email: darkard2003 <darkard2003@users.noreply.github.com>
License-Expression: GPL-3.0-or-later
Project-URL: Homepage, https://github.com/darkard2003/pymv
Project-URL: Repository, https://github.com/darkard2003/pymv
Project-URL: Issues, https://github.com/darkard2003/pymv/issues
Keywords: kitty,terminal,image-viewer,tui,pdf-viewer,image,viewer,graphics
Classifier: Development Status :: 4 - Beta
Classifier: Environment :: Console
Classifier: Intended Audience :: End Users/Desktop
Classifier: Operating System :: POSIX :: Linux
Classifier: Operating System :: MacOS
Classifier: Programming Language :: Python :: 3
Classifier: Programming Language :: Python :: 3.12
Classifier: Topic :: Multimedia :: Graphics :: Viewers
Classifier: Topic :: Terminals
Requires-Python: >=3.12
License-File: LICENSE
Requires-Dist: pillow>=11.3.0
Requires-Dist: pdf2image>=1.17.0
Provides-Extra: dev
Requires-Dist: build; extra == "dev"
Requires-Dist: twine; extra == "dev"
Dynamic: license-file
